{"directed": true, "multigraph": false, "graph": {}, "nodes": [{"attr": {"type": "class", "name": "WearableNavigationDrawerAdapter", "nullable": false}, "id": "src1820.java.WearableNavigationDrawerAdapter"}, {"attr": {"type": "method", "name": "getItemText", "nullable": false}, "id": "src1820.java.WearableNavigationDrawerAdapter.getItemText()"}, {"attr": {"type": "parameter", "name": "pos", "nullable": false}, "id": "src1820.java.WearableNavigationDrawerAdapter.getItemText().pos"}, {"attr": {"type": "method", "name": "getItemDrawable", "nullable": false}, "id": "src1820.java.WearableNavigationDrawerAdapter.getItemDrawable()"}, {"attr": {"type": "parameter", "name": "pos", "nullable": false}, "id": "src1820.java.WearableNavigationDrawerAdapter.getItemDrawable().pos"}, {"attr": {"type": "method", "name": "getCount", "nullable": false}, "id": "src1820.java.WearableNavigationDrawerAdapter.getCount()"}, {"attr": {"type": "method", "name": "notifyDataSetChanged", "nullable": false}, "id": "src1820.java.WearableNavigationDrawerAdapter.notifyDataSetChanged()"}, {"attr": {"type": "method", "name": "setPresenter", "nullable": false}, "id": "src1820.java.WearableNavigationDrawerAdapter.setPresenter()"}, {"attr": {"type": "parameter", "name": "presenter", "nullable": false}, "id": "src1820.java.WearableNavigationDrawerAdapter.setPresenter().presenter"}, {"attr": {"type": "field", "name": "mPresenter", "nullable": true}, "id": "src1820.java.WearableNavigationDrawerAdapter.mPresenter"}, {"attr": {"type": "literal", "name": "null", "nullable": false}, "id": "src1820.java.null_122_38"}, {"attr": {"type": "literal", "name": "null", "nullable": false}, "id": "src1820.java.null_139_22"}, {"attr": {"type": "literal", "name": "null", "nullable": false}, "id": "src1820.java.null_214_36"}, {"attr": {"type": "literal", "name": "null", "nullable": false}, "id": "src1820.java.null_276_31"}], "links": [{"type": "contains", "source": "src1820.java.WearableNavigationDrawerAdapter", "target": "src1820.java.WearableNavigationDrawerAdapter.getItemText()"}, {"type": "contains", "source": "src1820.java.WearableNavigationDrawerAdapter", "target": "src1820.java.WearableNavigationDrawerAdapter.getItemDrawable()"}, {"type": "contains", "source": "src1820.java.WearableNavigationDrawerAdapter", "target": "src1820.java.WearableNavigationDrawerAdapter.getCount()"}, {"type": "contains", "source": "src1820.java.WearableNavigationDrawerAdapter", "target": "src1820.java.WearableNavigationDrawerAdapter.notifyDataSetChanged()"}, {"type": "contains", "source": "src1820.java.WearableNavigationDrawerAdapter", "target": "src1820.java.WearableNavigationDrawerAdapter.setPresenter()"}, {"type": "has_field", "source": "src1820.java.WearableNavigationDrawerAdapter", "target": "src1820.java.WearableNavigationDrawerAdapter.mPresenter"}, {"type": "has_parameter", "source": "src1820.java.WearableNavigationDrawerAdapter.getItemText()", "target": "src1820.java.WearableNavigationDrawerAdapter.getItemText().pos"}, {"type": "has_parameter", "source": "src1820.java.WearableNavigationDrawerAdapter.getItemDrawable()", "target": "src1820.java.WearableNavigationDrawerAdapter.getItemDrawable().pos"}, {"type": "has_parameter", "source": "src1820.java.WearableNavigationDrawerAdapter.setPresenter()", "target": "src1820.java.WearableNavigationDrawerAdapter.setPresenter().presenter"}]}