{"directed": true, "multigraph": false, "graph": {}, "nodes": [{"attr": {"type": "file", "name": "src281.java", "nullable": false, "actual_type": null}, "id": "src281.java"}, {"attr": {"type": "class", "name": "JSDocSerializer", "nullable": false, "actual_type": null}, "id": "src281.java.JSDocSerializer"}, {"attr": {"type": "method", "name": "convertJSDocInfoForOptimizations", "nullable": false, "actual_type": null}, "id": "src281.java.JSDocSerializer.convertJSDocInfoForOptimizations()"}, {"attr": {"type": "parameter", "name": "jsdoc", "nullable": false, "actual_type": "JSDocInfo"}, "id": "src281.java.JSDocSerializer.convertJSDocInfoForOptimizations().jsdoc"}, {"attr": {"type": "method", "name": "serializeJsdoc", "nullable": true, "actual_type": null}, "id": "src281.java.JSDocSerializer.serializeJsdoc()"}, {"attr": {"type": "parameter", "name": "jsdoc", "nullable": false, "actual_type": "JSDocInfo"}, "id": "src281.java.JSDocSerializer.serializeJsdoc().jsdoc"}, {"attr": {"type": "parameter", "name": "stringPool", "nullable": false, "actual_type": "StringPool"}, "id": "src281.java.JSDocSerializer.serializeJsdoc().stringPool"}, {"attr": {"type": "method", "name": "serializeIdGenerator", "nullable": false, "actual_type": null}, "id": "src281.java.JSDocSerializer.serializeIdGenerator()"}, {"attr": {"type": "parameter", "name": "doc", "nullable": false, "actual_type": "JSDocInfo"}, "id": "src281.java.JSDocSerializer.serializeIdGenerator().doc"}, {"attr": {"type": "method", "name": "createPlaceholderType", "nullable": false, "actual_type": null}, "id": "src281.java.JSDocSerializer.createPlaceholderType()"}, {"attr": {"type": "method", "name": "deserializeJsdoc", "nullable": true, "actual_type": null}, "id": "src281.java.JSDocSerializer.deserializeJsdoc()"}, {"attr": {"type": "parameter", "name": "serializedJsdoc", "nullable": false, "actual_type": "OptimizationJsdoc"}, "id": "src281.java.JSDocSerializer.deserializeJsdoc().serializedJsdoc"}, {"attr": {"type": "parameter", "name": "stringPool", "nullable": false, "actual_type": "StringPool"}, "id": "src281.java.JSDocSerializer.deserializeJsdoc().stringPool"}, {"attr": {"type": "field", "name": "SYNTHETIC_SOURCE", "nullable": false, "actual_type": null}, "id": "src281.java.JSDocSerializer.SYNTHETIC_SOURCE"}, {"attr": {"type": "field", "name": "PLACEHOLDER_TYPE_NAME", "nullable": false, "actual_type": null}, "id": "src281.java.JSDocSerializer.PLACEHOLDER_TYPE_NAME"}, {"attr": {"type": "field", "name": "placeholderType", "nullable": false, "actual_type": null}, "id": "src281.java.JSDocSerializer.placeholderType"}, {"attr": {"type": "literal", "name": "null", "nullable": false, "actual_type": null}, "id": "src281.java.null_50_18"}, {"attr": {"type": "literal", "name": "null", "nullable": false, "actual_type": null}, "id": "src281.java.null_51_14"}, {"attr": {"type": "literal", "name": "null", "nullable": false, "actual_type": null}, "id": "src281.java.null_60_31"}, {"attr": {"type": "literal", "name": "null", "nullable": false, "actual_type": null}, "id": "src281.java.null_151_35"}, {"attr": {"type": "literal", "name": "null", "nullable": false, "actual_type": null}, "id": "src281.java.null_154_42"}, {"attr": {"type": "literal", "name": "null", "nullable": false, "actual_type": null}, "id": "src281.java.null_157_31"}, {"attr": {"type": "literal", "name": "null", "nullable": false, "actual_type": null}, "id": "src281.java.null_169_14"}, {"attr": {"type": "literal", "name": "null", "nullable": false, "actual_type": null}, "id": "src281.java.null_210_28"}, {"attr": {"type": "literal", "name": "null", "nullable": false, "actual_type": null}, "id": "src281.java.null_211_14"}, {"attr": {"type": "literal", "name": "null", "nullable": false, "actual_type": null}, "id": "src281.java.null_229_32"}, {"attr": {"type": "literal", "name": "null", "nullable": false, "actual_type": null}, "id": "src281.java.null_230_36"}, {"attr": {"type": "literal", "name": "null", "nullable": false, "actual_type": null}, "id": "src281.java.null_274_35"}, {"attr": {"type": "literal", "name": "null", "nullable": false, "actual_type": null}, "id": "src281.java.null_278_35"}, {"attr": {"type": "literal", "name": "null", "nullable": false, "actual_type": null}, "id": "src281.java.null_291_43"}, {"attr": {"type": "literal", "name": "null", "nullable": false, "actual_type": null}, "id": "src281.java.null_322_43"}, {"attr": {"type": "literal", "name": "null", "nullable": false, "actual_type": null}, "id": "src281.java.null_331_43"}, {"attr": {"type": "literal", "name": "null", "nullable": false, "actual_type": null}, "id": "src281.java.null_349_21"}, {"attr": {"type": "literal", "name": "null", "nullable": false, "actual_type": null}, "id": "src281.java.null_352_25"}], "links": [{"type": "contains", "source": "src281.java", "target": "src281.java.JSDocSerializer"}, {"type": "contains", "source": "src281.java.JSDocSerializer", "target": "src281.java.JSDocSerializer.convertJSDocInfoForOptimizations()"}, {"type": "contains", "source": "src281.java.JSDocSerializer", "target": "src281.java.JSDocSerializer.serializeJsdoc()"}, {"type": "contains", "source": "src281.java.JSDocSerializer", "target": "src281.java.JSDocSerializer.serializeIdGenerator()"}, {"type": "contains", "source": "src281.java.JSDocSerializer", "target": "src281.java.JSDocSerializer.createPlaceholderType()"}, {"type": "contains", "source": "src281.java.JSDocSerializer", "target": "src281.java.JSDocSerializer.deserializeJsdoc()"}, {"type": "has_field", "source": "src281.java.JSDocSerializer", "target": "src281.java.JSDocSerializer.SYNTHETIC_SOURCE"}, {"type": "has_field", "source": "src281.java.JSDocSerializer", "target": "src281.java.JSDocSerializer.PLACEHOLDER_TYPE_NAME"}, {"type": "has_field", "source": "src281.java.JSDocSerializer", "target": "src281.java.JSDocSerializer.placeholderType"}, {"type": "has_parameter", "source": "src281.java.JSDocSerializer.convertJSDocInfoForOptimizations()", "target": "src281.java.JSDocSerializer.convertJSDocInfoForOptimizations().jsdoc"}, {"type": "has_parameter", "source": "src281.java.JSDocSerializer.serializeJsdoc()", "target": "src281.java.JSDocSerializer.serializeJsdoc().jsdoc"}, {"type": "has_parameter", "source": "src281.java.JSDocSerializer.serializeJsdoc()", "target": "src281.java.JSDocSerializer.serializeJsdoc().stringPool"}, {"type": "has_parameter", "source": "src281.java.JSDocSerializer.serializeIdGenerator()", "target": "src281.java.JSDocSerializer.serializeIdGenerator().doc"}, {"type": "has_parameter", "source": "src281.java.JSDocSerializer.deserializeJsdoc()", "target": "src281.java.JSDocSerializer.deserializeJsdoc().serializedJsdoc"}, {"type": "has_parameter", "source": "src281.java.JSDocSerializer.deserializeJsdoc()", "target": "src281.java.JSDocSerializer.deserializeJsdoc().stringPool"}]}