{"directed": true, "multigraph": false, "graph": {}, "nodes": [{"attr": {"type": "file", "name": "src3072.java", "nullable": false, "actual_type": null}, "id": "src3072.java"}, {"attr": {"type": "class", "name": "TransactionSynchronizationManager", "nullable": false, "actual_type": null}, "id": "src3072.java.TransactionSynchronizationManager"}, {"attr": {"type": "method", "name": "forCurrentTransaction", "nullable": false, "actual_type": null}, "id": "src3072.java.TransactionSynchronizationManager.forCurrentTransaction()"}, {"attr": {"type": "method", "name": "hasResource", "nullable": false, "actual_type": null}, "id": "src3072.java.TransactionSynchronizationManager.hasResource()"}, {"attr": {"type": "parameter", "name": "key", "nullable": false, "actual_type": "Object"}, "id": "src3072.java.TransactionSynchronizationManager.hasResource().key"}, {"attr": {"type": "method", "name": "getResource", "nullable": true, "actual_type": null}, "id": "src3072.java.TransactionSynchronizationManager.getResource()"}, {"attr": {"type": "parameter", "name": "key", "nullable": false, "actual_type": "Object"}, "id": "src3072.java.TransactionSynchronizationManager.getResource().key"}, {"attr": {"type": "method", "name": "doGetResource", "nullable": true, "actual_type": null}, "id": "src3072.java.TransactionSynchronizationManager.doGetResource()"}, {"attr": {"type": "parameter", "name": "actualKey", "nullable": false, "actual_type": "Object"}, "id": "src3072.java.TransactionSynchronizationManager.doGetResource().actualKey"}, {"attr": {"type": "method", "name": "bindResource", "nullable": false, "actual_type": null}, "id": "src3072.java.TransactionSynchronizationManager.bindResource()"}, {"attr": {"type": "parameter", "name": "key", "nullable": false, "actual_type": "Object"}, "id": "src3072.java.TransactionSynchronizationManager.bindResource().key"}, {"attr": {"type": "parameter", "name": "value", "nullable": false, "actual_type": "Object"}, "id": "src3072.java.TransactionSynchronizationManager.bindResource().value"}, {"attr": {"type": "method", "name": "unbindResource", "nullable": false, "actual_type": null}, "id": "src3072.java.TransactionSynchronizationManager.unbindResource()"}, {"attr": {"type": "parameter", "name": "key", "nullable": false, "actual_type": "Object"}, "id": "src3072.java.TransactionSynchronizationManager.unbindResource().key"}, {"attr": {"type": "method", "name": "unbindResourceIfPossible", "nullable": true, "actual_type": null}, "id": "src3072.java.TransactionSynchronizationManager.unbindResourceIfPossible()"}, {"attr": {"type": "parameter", "name": "key", "nullable": false, "actual_type": "Object"}, "id": "src3072.java.TransactionSynchronizationManager.unbindResourceIfPossible().key"}, {"attr": {"type": "method", "name": "doUnbindResource", "nullable": true, "actual_type": null}, "id": "src3072.java.TransactionSynchronizationManager.doUnbindResource()"}, {"attr": {"type": "parameter", "name": "actualKey", "nullable": false, "actual_type": "Object"}, "id": "src3072.java.TransactionSynchronizationManager.doUnbindResource().actualKey"}, {"attr": {"type": "method", "name": "isSynchronizationActive", "nullable": false, "actual_type": null}, "id": "src3072.java.TransactionSynchronizationManager.isSynchronizationActive()"}, {"attr": {"type": "method", "name": "initSynchronization", "nullable": false, "actual_type": null}, "id": "src3072.java.TransactionSynchronizationManager.initSynchronization()"}, {"attr": {"type": "method", "name": "registerSynchronization", "nullable": false, "actual_type": null}, "id": "src3072.java.TransactionSynchronizationManager.registerSynchronization()"}, {"attr": {"type": "parameter", "name": "synchronization", "nullable": false, "actual_type": "TransactionSynchronization"}, "id": "src3072.java.TransactionSynchronizationManager.registerSynchronization().synchronization"}, {"attr": {"type": "method", "name": "getSynchronizations", "nullable": false, "actual_type": null}, "id": "src3072.java.TransactionSynchronizationManager.getSynchronizations()"}, {"attr": {"type": "method", "name": "clearSynchronization", "nullable": false, "actual_type": null}, "id": "src3072.java.TransactionSynchronizationManager.clearSynchronization()"}, {"attr": {"type": "method", "name": "setCurrentTransactionName", "nullable": false, "actual_type": null}, "id": "src3072.java.TransactionSynchronizationManager.setCurrentTransactionName()"}, {"attr": {"type": "parameter", "name": "name", "nullable": true, "actual_type": "String"}, "id": "src3072.java.TransactionSynchronizationManager.setCurrentTransactionName().name"}, {"attr": {"type": "method", "name": "getCurrentTransactionName", "nullable": true, "actual_type": null}, "id": "src3072.java.TransactionSynchronizationManager.getCurrentTransactionName()"}, {"attr": {"type": "method", "name": "setCurrentTransactionReadOnly", "nullable": false, "actual_type": null}, "id": "src3072.java.TransactionSynchronizationManager.setCurrentTransactionReadOnly()"}, {"attr": {"type": "parameter", "name": "readOnly", "nullable": false, "actual_type": "boolean"}, "id": "src3072.java.TransactionSynchronizationManager.setCurrentTransactionReadOnly().readOnly"}, {"attr": {"type": "method", "name": "isCurrentTransactionReadOnly", "nullable": false, "actual_type": null}, "id": "src3072.java.TransactionSynchronizationManager.isCurrentTransactionReadOnly()"}, {"attr": {"type": "method", "name": "setCurrentTransactionIsolationLevel", "nullable": false, "actual_type": null}, "id": "src3072.java.TransactionSynchronizationManager.setCurrentTransactionIsolationLevel()"}, {"attr": {"type": "parameter", "name": "isolationLevel", "nullable": true, "actual_type": "Integer"}, "id": "src3072.java.TransactionSynchronizationManager.setCurrentTransactionIsolationLevel().isolationLevel"}, {"attr": {"type": "method", "name": "getCurrentTransactionIsolationLevel", "nullable": true, "actual_type": null}, "id": "src3072.java.TransactionSynchronizationManager.getCurrentTransactionIsolationLevel()"}, {"attr": {"type": "method", "name": "setActualTransactionActive", "nullable": false, "actual_type": null}, "id": "src3072.java.TransactionSynchronizationManager.setActualTransactionActive()"}, {"attr": {"type": "parameter", "name": "active", "nullable": false, "actual_type": "boolean"}, "id": "src3072.java.TransactionSynchronizationManager.setActualTransactionActive().active"}, {"attr": {"type": "method", "name": "isActualTransactionActive", "nullable": false, "actual_type": null}, "id": "src3072.java.TransactionSynchronizationManager.isActualTransactionActive()"}, {"attr": {"type": "method", "name": "clear", "nullable": false, "actual_type": null}, "id": "src3072.java.TransactionSynchronizationManager.clear()"}, {"attr": {"type": "field", "name": "transactionContext", "nullable": false, "actual_type": null}, "id": "src3072.java.TransactionSynchronizationManager.transactionContext"}, {"attr": {"type": "literal", "name": "null", "nullable": false, "actual_type": null}, "id": "src3072.java.null_99_20"}, {"attr": {"type": "literal", "name": "null", "nullable": false, "actual_type": null}, "id": "src3072.java.null_133_19"}, {"attr": {"type": "literal", "name": "null", "nullable": false, "actual_type": null}, "id": "src3072.java.null_148_16"}, {"attr": {"type": "literal", "name": "null", "nullable": false, "actual_type": null}, "id": "src3072.java.null_185_60"}, {"attr": {"type": "literal", "name": "null", "nullable": false, "actual_type": null}, "id": "src3072.java.null_215_17"}, {"attr": {"type": "literal", "name": "null", "nullable": false, "actual_type": null}, "id": "src3072.java.null_230_17"}, {"attr": {"type": "literal", "name": "null", "nullable": false, "actual_type": null}, "id": "src3072.java.null_256_47"}, {"id": "src3072.java.setSynchronizations"}], "links": [{"type": "contains", "source": "src3072.java", "target": "src3072.java.TransactionSynchronizationManager"}, {"type": "contains", "source": "src3072.java.TransactionSynchronizationManager", "target": "src3072.java.TransactionSynchronizationManager.forCurrentTransaction()"}, {"type": "contains", "source": "src3072.java.TransactionSynchronizationManager", "target": "src3072.java.TransactionSynchronizationManager.hasResource()"}, {"type": "contains", "source": "src3072.java.TransactionSynchronizationManager", "target": "src3072.java.TransactionSynchronizationManager.getResource()"}, {"type": "contains", "source": "src3072.java.TransactionSynchronizationManager", "target": "src3072.java.TransactionSynchronizationManager.doGetResource()"}, {"type": "contains", "source": "src3072.java.TransactionSynchronizationManager", "target": "src3072.java.TransactionSynchronizationManager.bindResource()"}, {"type": "contains", "source": "src3072.java.TransactionSynchronizationManager", "target": "src3072.java.TransactionSynchronizationManager.unbindResource()"}, {"type": "contains", "source": "src3072.java.TransactionSynchronizationManager", "target": "src3072.java.TransactionSynchronizationManager.unbindResourceIfPossible()"}, {"type": "contains", "source": "src3072.java.TransactionSynchronizationManager", "target": "src3072.java.TransactionSynchronizationManager.doUnbindResource()"}, {"type": "contains", "source": "src3072.java.TransactionSynchronizationManager", "target": "src3072.java.TransactionSynchronizationManager.isSynchronizationActive()"}, {"type": "contains", "source": "src3072.java.TransactionSynchronizationManager", "target": "src3072.java.TransactionSynchronizationManager.initSynchronization()"}, {"type": "contains", "source": "src3072.java.TransactionSynchronizationManager", "target": "src3072.java.TransactionSynchronizationManager.registerSynchronization()"}, {"type": "contains", "source": "src3072.java.TransactionSynchronizationManager", "target": "src3072.java.TransactionSynchronizationManager.getSynchronizations()"}, {"type": "contains", "source": "src3072.java.TransactionSynchronizationManager", "target": "src3072.java.TransactionSynchronizationManager.clearSynchronization()"}, {"type": "contains", "source": "src3072.java.TransactionSynchronizationManager", "target": "src3072.java.TransactionSynchronizationManager.setCurrentTransactionName()"}, {"type": "contains", "source": "src3072.java.TransactionSynchronizationManager", "target": "src3072.java.TransactionSynchronizationManager.getCurrentTransactionName()"}, {"type": "contains", "source": "src3072.java.TransactionSynchronizationManager", "target": "src3072.java.TransactionSynchronizationManager.setCurrentTransactionReadOnly()"}, {"type": "contains", "source": "src3072.java.TransactionSynchronizationManager", "target": "src3072.java.TransactionSynchronizationManager.isCurrentTransactionReadOnly()"}, {"type": "contains", "source": "src3072.java.TransactionSynchronizationManager", "target": "src3072.java.TransactionSynchronizationManager.setCurrentTransactionIsolationLevel()"}, {"type": "contains", "source": "src3072.java.TransactionSynchronizationManager", "target": "src3072.java.TransactionSynchronizationManager.getCurrentTransactionIsolationLevel()"}, {"type": "contains", "source": "src3072.java.TransactionSynchronizationManager", "target": "src3072.java.TransactionSynchronizationManager.setActualTransactionActive()"}, {"type": "contains", "source": "src3072.java.TransactionSynchronizationManager", "target": "src3072.java.TransactionSynchronizationManager.isActualTransactionActive()"}, {"type": "contains", "source": "src3072.java.TransactionSynchronizationManager", "target": "src3072.java.TransactionSynchronizationManager.clear()"}, {"type": "has_field", "source": "src3072.java.TransactionSynchronizationManager", "target": "src3072.java.TransactionSynchronizationManager.transactionContext"}, {"type": "has_parameter", "source": "src3072.java.TransactionSynchronizationManager.hasResource()", "target": "src3072.java.TransactionSynchronizationManager.hasResource().key"}, {"type": "has_parameter", "source": "src3072.java.TransactionSynchronizationManager.getResource()", "target": "src3072.java.TransactionSynchronizationManager.getResource().key"}, {"type": "has_parameter", "source": "src3072.java.TransactionSynchronizationManager.doGetResource()", "target": "src3072.java.TransactionSynchronizationManager.doGetResource().actualKey"}, {"type": "has_parameter", "source": "src3072.java.TransactionSynchronizationManager.bindResource()", "target": "src3072.java.TransactionSynchronizationManager.bindResource().key"}, {"type": "has_parameter", "source": "src3072.java.TransactionSynchronizationManager.bindResource()", "target": "src3072.java.TransactionSynchronizationManager.bindResource().value"}, {"type": "has_parameter", "source": "src3072.java.TransactionSynchronizationManager.unbindResource()", "target": "src3072.java.TransactionSynchronizationManager.unbindResource().key"}, {"type": "has_parameter", "source": "src3072.java.TransactionSynchronizationManager.unbindResourceIfPossible()", "target": "src3072.java.TransactionSynchronizationManager.unbindResourceIfPossible().key"}, {"type": "has_parameter", "source": "src3072.java.TransactionSynchronizationManager.doUnbindResource()", "target": "src3072.java.TransactionSynchronizationManager.doUnbindResource().actualKey"}, {"type": "has_parameter", "source": "src3072.java.TransactionSynchronizationManager.registerSynchronization()", "target": "src3072.java.TransactionSynchronizationManager.registerSynchronization().synchronization"}, {"type": "has_parameter", "source": "src3072.java.TransactionSynchronizationManager.setCurrentTransactionName()", "target": "src3072.java.TransactionSynchronizationManager.setCurrentTransactionName().name"}, {"type": "has_parameter", "source": "src3072.java.TransactionSynchronizationManager.setCurrentTransactionReadOnly()", "target": "src3072.java.TransactionSynchronizationManager.setCurrentTransactionReadOnly().readOnly"}, {"type": "has_parameter", "source": "src3072.java.TransactionSynchronizationManager.setCurrentTransactionIsolationLevel()", "target": "src3072.java.TransactionSynchronizationManager.setCurrentTransactionIsolationLevel().isolationLevel"}, {"type": "has_parameter", "source": "src3072.java.TransactionSynchronizationManager.setActualTransactionActive()", "target": "src3072.java.TransactionSynchronizationManager.setActualTransactionActive().active"}, {"type": "contains", "source": "src3072.java.setSynchronizations", "target": "src3072.java.null_256_47"}]}