{"directed": true, "multigraph": false, "graph": {}, "nodes": [{"attr": {"type": "file", "name": "src3387.java", "line_number": null, "nullable": false, "actual_type": null}, "id": "src3387.java"}, {"attr": {"type": "class", "name": "ContentNegotiationConfigurer", "line_number": 97, "nullable": false, "actual_type": null}, "id": "src3387.java.ContentNegotiationConfigurer"}, {"attr": {"type": "method", "name": "strategies", "line_number": 122, "nullable": false, "actual_type": null}, "id": "src3387.java.ContentNegotiationConfigurer.strategies()"}, {"attr": {"type": "parameter", "name": "strategies", "line_number": 122, "nullable": true, "actual_type": "List"}, "id": "src3387.java.ContentNegotiationConfigurer.strategies().strategies"}, {"attr": {"type": "method", "name": "favorParameter", "line_number": 133, "nullable": false, "actual_type": null}, "id": "src3387.java.ContentNegotiationConfigurer.favorParameter()"}, {"attr": {"type": "parameter", "name": "favorParameter", "line_number": 133, "nullable": false, "actual_type": "boolean"}, "id": "src3387.java.ContentNegotiationConfigurer.favorParameter().favorParameter"}, {"attr": {"type": "method", "name": "parameterName", "line_number": 142, "nullable": false, "actual_type": null}, "id": "src3387.java.ContentNegotiationConfigurer.parameterName()"}, {"attr": {"type": "parameter", "name": "parameterName", "line_number": 142, "nullable": false, "actual_type": "String"}, "id": "src3387.java.ContentNegotiationConfigurer.parameterName().parameterName"}, {"attr": {"type": "method", "name": "favorPathExtension", "line_number": 156, "nullable": false, "actual_type": null}, "id": "src3387.java.ContentNegotiationConfigurer.favorPathExtension()"}, {"attr": {"type": "parameter", "name": "favorPathExtension", "line_number": 156, "nullable": false, "actual_type": "boolean"}, "id": "src3387.java.ContentNegotiationConfigurer.favorPathExtension().favorPathExtension"}, {"attr": {"type": "method", "name": "mediaType", "line_number": 176, "nullable": false, "actual_type": null}, "id": "src3387.java.ContentNegotiationConfigurer.mediaType()"}, {"attr": {"type": "parameter", "name": "extension", "line_number": 176, "nullable": false, "actual_type": "String"}, "id": "src3387.java.ContentNegotiationConfigurer.mediaType().extension"}, {"attr": {"type": "parameter", "name": "mediaType", "line_number": 176, "nullable": false, "actual_type": "MediaType"}, "id": "src3387.java.ContentNegotiationConfigurer.mediaType().mediaType"}, {"attr": {"type": "method", "name": "mediaTypes", "line_number": 186, "nullable": false, "actual_type": null}, "id": "src3387.java.ContentNegotiationConfigurer.mediaTypes()"}, {"attr": {"type": "parameter", "name": "mediaTypes", "line_number": 186, "nullable": true, "actual_type": "Map"}, "id": "src3387.java.ContentNegotiationConfigurer.mediaTypes().mediaTypes"}, {"attr": {"type": "method", "name": "replaceMediaTypes", "line_number": 198, "nullable": false, "actual_type": null}, "id": "src3387.java.ContentNegotiationConfigurer.replaceMediaTypes()"}, {"attr": {"type": "parameter", "name": "mediaTypes", "line_number": 198, "nullable": false, "actual_type": "Map"}, "id": "src3387.java.ContentNegotiationConfigurer.replaceMediaTypes().mediaTypes"}, {"attr": {"type": "method", "name": "ignoreUnknownPathExtensions", "line_number": 213, "nullable": false, "actual_type": null}, "id": "src3387.java.ContentNegotiationConfigurer.ignoreUnknownPathExtensions()"}, {"attr": {"type": "parameter", "name": "ignore", "line_number": 213, "nullable": false, "actual_type": "boolean"}, "id": "src3387.java.ContentNegotiationConfigurer.ignoreUnknownPathExtensions().ignore"}, {"attr": {"type": "method", "name": "useJaf", "line_number": 226, "nullable": false, "actual_type": null}, "id": "src3387.java.ContentNegotiationConfigurer.useJaf()"}, {"attr": {"type": "parameter", "name": "useJaf", "line_number": 226, "nullable": false, "actual_type": "boolean"}, "id": "src3387.java.ContentNegotiationConfigurer.useJaf().useJaf"}, {"attr": {"type": "method", "name": "useRegisteredExtensionsOnly", "line_number": 237, "nullable": false, "actual_type": null}, "id": "src3387.java.ContentNegotiationConfigurer.useRegisteredExtensionsOnly()"}, {"attr": {"type": "parameter", "name": "useRegisteredExtensionsOnly", "line_number": 237, "nullable": false, "actual_type": "boolean"}, "id": "src3387.java.ContentNegotiationConfigurer.useRegisteredExtensionsOnly().useRegisteredExtensionsOnly"}, {"attr": {"type": "method", "name": "ignoreAcceptHeader", "line_number": 246, "nullable": false, "actual_type": null}, "id": "src3387.java.ContentNegotiationConfigurer.ignoreAcceptHeader()"}, {"attr": {"type": "parameter", "name": "ignoreAcceptHeader", "line_number": 246, "nullable": false, "actual_type": "boolean"}, "id": "src3387.java.ContentNegotiationConfigurer.ignoreAcceptHeader().ignoreAcceptHeader"}, {"attr": {"type": "method", "name": "defaultContentType", "line_number": 259, "nullable": false, "actual_type": null}, "id": "src3387.java.ContentNegotiationConfigurer.defaultContentType()"}, {"attr": {"type": "parameter", "name": "defaultContentTypes", "line_number": 259, "nullable": false, "actual_type": "MediaType"}, "id": "src3387.java.ContentNegotiationConfigurer.defaultContentType().defaultContentTypes"}, {"attr": {"type": "method", "name": "defaultContentTypeStrategy", "line_number": 271, "nullable": false, "actual_type": null}, "id": "src3387.java.ContentNegotiationConfigurer.defaultContentTypeStrategy()"}, {"attr": {"type": "parameter", "name": "defaultStrategy", "line_number": 271, "nullable": false, "actual_type": "ContentNegotiationStrategy"}, "id": "src3387.java.ContentNegotiationConfigurer.defaultContentTypeStrategy().defaultStrategy"}, {"attr": {"type": "method", "name": "buildContentNegotiationManager", "line_number": 282, "nullable": false, "actual_type": null}, "id": "src3387.java.ContentNegotiationConfigurer.buildContentNegotiationManager()"}, {"attr": {"type": "field", "name": "factory", "line_number": null, "nullable": false, "actual_type": null}, "id": "src3387.java.ContentNegotiationConfigurer.factory"}, {"attr": {"type": "field", "name": "mediaTypes", "line_number": null, "nullable": false, "actual_type": null}, "id": "src3387.java.ContentNegotiationConfigurer.mediaTypes"}, {"attr": {"type": "variable", "name": "factory", "line_number": null, "nullable": false, "actual_type": null}, "id": "src3387.java.factory"}, {"attr": {"type": "variable", "name": "mediaTypes", "line_number": null, "nullable": false, "actual_type": null}, "id": "src3387.java.mediaTypes"}, {"attr": {"type": "literal", "name": "null", "line_number": 108, "nullable": false, "actual_type": null}, "id": "src3387.java.null_108_25"}, {"attr": {"type": "method", "name": "strategies", "line_number": 122, "nullable": false, "actual_type": null}, "id": "src3387.java.strategies()"}, {"attr": {"type": "parameter", "name": "strategies", "line_number": 122, "nullable": false, "actual_type": "List"}, "id": "src3387.java.strategies().strategies"}, {"attr": {"type": "method", "name": "favorParameter", "line_number": 133, "nullable": false, "actual_type": null}, "id": "src3387.java.favorParameter()"}, {"attr": {"type": "parameter", "name": "favorParameter", "line_number": 133, "nullable": false, "actual_type": "boolean"}, "id": "src3387.java.favorParameter().favorParameter"}, {"attr": {"type": "method", "name": "parameterName", "line_number": 142, "nullable": false, "actual_type": null}, "id": "src3387.java.parameterName()"}, {"attr": {"type": "parameter", "name": "parameterName", "line_number": 142, "nullable": false, "actual_type": "String"}, "id": "src3387.java.parameterName().parameterName"}, {"attr": {"type": "method", "name": "favorPathExtension", "line_number": 156, "nullable": false, "actual_type": null}, "id": "src3387.java.favorPathExtension()"}, {"attr": {"type": "parameter", "name": "favorPathExtension", "line_number": 156, "nullable": false, "actual_type": "boolean"}, "id": "src3387.java.favorPathExtension().favorPathExtension"}, {"attr": {"type": "method", "name": "mediaType", "line_number": 176, "nullable": false, "actual_type": null}, "id": "src3387.java.mediaType()"}, {"attr": {"type": "parameter", "name": "extension", "line_number": 176, "nullable": false, "actual_type": "String"}, "id": "src3387.java.mediaType().extension"}, {"attr": {"type": "parameter", "name": "mediaType", "line_number": 176, "nullable": false, "actual_type": "MediaType"}, "id": "src3387.java.mediaType().mediaType"}, {"attr": {"type": "method", "name": "mediaTypes", "line_number": 186, "nullable": false, "actual_type": null}, "id": "src3387.java.mediaTypes()"}, {"attr": {"type": "parameter", "name": "mediaTypes", "line_number": 186, "nullable": false, "actual_type": "Map"}, "id": "src3387.java.mediaTypes().mediaTypes"}, {"attr": {"type": "literal", "name": "null", "line_number": 187, "nullable": false, "actual_type": null}, "id": "src3387.java.null_187_21"}, {"attr": {"type": "method", "name": "replaceMediaTypes", "line_number": 198, "nullable": false, "actual_type": null}, "id": "src3387.java.replaceMediaTypes()"}, {"attr": {"type": "parameter", "name": "mediaTypes", "line_number": 198, "nullable": false, "actual_type": "Map"}, "id": "src3387.java.replaceMediaTypes().mediaTypes"}, {"attr": {"type": "method", "name": "ignoreUnknownPathExtensions", "line_number": 213, "nullable": false, "actual_type": null}, "id": "src3387.java.ignoreUnknownPathExtensions()"}, {"attr": {"type": "parameter", "name": "ignore", "line_number": 213, "nullable": false, "actual_type": "boolean"}, "id": "src3387.java.ignoreUnknownPathExtensions().ignore"}, {"attr": {"type": "method", "name": "useJaf", "line_number": 226, "nullable": false, "actual_type": null}, "id": "src3387.java.useJaf()"}, {"attr": {"type": "parameter", "name": "useJaf", "line_number": 226, "nullable": false, "actual_type": "boolean"}, "id": "src3387.java.useJaf().useJaf"}, {"attr": {"type": "method", "name": "useRegisteredExtensionsOnly", "line_number": 237, "nullable": false, "actual_type": null}, "id": "src3387.java.useRegisteredExtensionsOnly()"}, {"attr": {"type": "parameter", "name": "useRegisteredExtensionsOnly", "line_number": 237, "nullable": false, "actual_type": "boolean"}, "id": "src3387.java.useRegisteredExtensionsOnly().useRegisteredExtensionsOnly"}, {"attr": {"type": "method", "name": "ignoreAcceptHeader", "line_number": 246, "nullable": false, "actual_type": null}, "id": "src3387.java.ignoreAcceptHeader()"}, {"attr": {"type": "parameter", "name": "ignoreAcceptHeader", "line_number": 246, "nullable": false, "actual_type": "boolean"}, "id": "src3387.java.ignoreAcceptHeader().ignoreAcceptHeader"}, {"attr": {"type": "method", "name": "defaultContentType", "line_number": 259, "nullable": false, "actual_type": null}, "id": "src3387.java.defaultContentType()"}, {"attr": {"type": "parameter", "name": "defaultContentTypes", "line_number": 259, "nullable": false, "actual_type": "MediaType"}, "id": "src3387.java.defaultContentType().defaultContentTypes"}, {"attr": {"type": "method", "name": "defaultContentTypeStrategy", "line_number": 271, "nullable": false, "actual_type": null}, "id": "src3387.java.defaultContentTypeStrategy()"}, {"attr": {"type": "parameter", "name": "defaultStrategy", "line_number": 271, "nullable": false, "actual_type": "ContentNegotiationStrategy"}, "id": "src3387.java.defaultContentTypeStrategy().defaultStrategy"}, {"attr": {"type": "method", "name": "buildContentNegotiationManager", "line_number": 282, "nullable": false, "actual_type": null}, "id": "src3387.java.buildContentNegotiationManager()"}], "links": [{"type": "contains", "source": "src3387.java", "target": "src3387.java.ContentNegotiationConfigurer"}, {"type": "has_field", "source": "src3387.java", "target": "src3387.java.factory"}, {"type": "has_field", "source": "src3387.java", "target": "src3387.java.mediaTypes"}, {"type": "contains", "source": "src3387.java.ContentNegotiationConfigurer", "target": "src3387.java.ContentNegotiationConfigurer.strategies()"}, {"type": "contains", "source": "src3387.java.ContentNegotiationConfigurer", "target": "src3387.java.ContentNegotiationConfigurer.favorParameter()"}, {"type": "contains", "source": "src3387.java.ContentNegotiationConfigurer", "target": "src3387.java.ContentNegotiationConfigurer.parameterName()"}, {"type": "contains", "source": "src3387.java.ContentNegotiationConfigurer", "target": "src3387.java.ContentNegotiationConfigurer.favorPathExtension()"}, {"type": "contains", "source": "src3387.java.ContentNegotiationConfigurer", "target": "src3387.java.ContentNegotiationConfigurer.mediaType()"}, {"type": "contains", "source": "src3387.java.ContentNegotiationConfigurer", "target": "src3387.java.ContentNegotiationConfigurer.mediaTypes()"}, {"type": "contains", "source": "src3387.java.ContentNegotiationConfigurer", "target": "src3387.java.ContentNegotiationConfigurer.replaceMediaTypes()"}, {"type": "contains", "source": "src3387.java.ContentNegotiationConfigurer", "target": "src3387.java.ContentNegotiationConfigurer.ignoreUnknownPathExtensions()"}, {"type": "contains", "source": "src3387.java.ContentNegotiationConfigurer", "target": "src3387.java.ContentNegotiationConfigurer.useJaf()"}, {"type": "contains", "source": "src3387.java.ContentNegotiationConfigurer", "target": "src3387.java.ContentNegotiationConfigurer.useRegisteredExtensionsOnly()"}, {"type": "contains", "source": "src3387.java.ContentNegotiationConfigurer", "target": "src3387.java.ContentNegotiationConfigurer.ignoreAcceptHeader()"}, {"type": "contains", "source": "src3387.java.ContentNegotiationConfigurer", "target": "src3387.java.ContentNegotiationConfigurer.defaultContentType()"}, {"type": "contains", "source": "src3387.java.ContentNegotiationConfigurer", "target": "src3387.java.ContentNegotiationConfigurer.defaultContentTypeStrategy()"}, {"type": "contains", "source": "src3387.java.ContentNegotiationConfigurer", "target": "src3387.java.ContentNegotiationConfigurer.buildContentNegotiationManager()"}, {"type": "has_field", "source": "src3387.java.ContentNegotiationConfigurer", "target": "src3387.java.ContentNegotiationConfigurer.factory"}, {"type": "has_field", "source": "src3387.java.ContentNegotiationConfigurer", "target": "src3387.java.ContentNegotiationConfigurer.mediaTypes"}, {"type": "has_parameter", "source": "src3387.java.ContentNegotiationConfigurer.strategies()", "target": "src3387.java.ContentNegotiationConfigurer.strategies().strategies"}, {"type": "has_parameter", "source": "src3387.java.ContentNegotiationConfigurer.favorParameter()", "target": "src3387.java.ContentNegotiationConfigurer.favorParameter().favorParameter"}, {"type": "has_parameter", "source": "src3387.java.ContentNegotiationConfigurer.parameterName()", "target": "src3387.java.ContentNegotiationConfigurer.parameterName().parameterName"}, {"type": "has_parameter", "source": "src3387.java.ContentNegotiationConfigurer.favorPathExtension()", "target": "src3387.java.ContentNegotiationConfigurer.favorPathExtension().favorPathExtension"}, {"type": "has_parameter", "source": "src3387.java.ContentNegotiationConfigurer.mediaType()", "target": "src3387.java.ContentNegotiationConfigurer.mediaType().extension"}, {"type": "has_parameter", "source": "src3387.java.ContentNegotiationConfigurer.mediaType()", "target": "src3387.java.ContentNegotiationConfigurer.mediaType().mediaType"}, {"type": "has_parameter", "source": "src3387.java.ContentNegotiationConfigurer.mediaTypes()", "target": "src3387.java.ContentNegotiationConfigurer.mediaTypes().mediaTypes"}, {"type": "has_parameter", "source": "src3387.java.ContentNegotiationConfigurer.replaceMediaTypes()", "target": "src3387.java.ContentNegotiationConfigurer.replaceMediaTypes().mediaTypes"}, {"type": "has_parameter", "source": "src3387.java.ContentNegotiationConfigurer.ignoreUnknownPathExtensions()", "target": "src3387.java.ContentNegotiationConfigurer.ignoreUnknownPathExtensions().ignore"}, {"type": "has_parameter", "source": "src3387.java.ContentNegotiationConfigurer.useJaf()", "target": "src3387.java.ContentNegotiationConfigurer.useJaf().useJaf"}, {"type": "has_parameter", "source": "src3387.java.ContentNegotiationConfigurer.useRegisteredExtensionsOnly()", "target": "src3387.java.ContentNegotiationConfigurer.useRegisteredExtensionsOnly().useRegisteredExtensionsOnly"}, {"type": "has_parameter", "source": "src3387.java.ContentNegotiationConfigurer.ignoreAcceptHeader()", "target": "src3387.java.ContentNegotiationConfigurer.ignoreAcceptHeader().ignoreAcceptHeader"}, {"type": "has_parameter", "source": "src3387.java.ContentNegotiationConfigurer.defaultContentType()", "target": "src3387.java.ContentNegotiationConfigurer.defaultContentType().defaultContentTypes"}, {"type": "has_parameter", "source": "src3387.java.ContentNegotiationConfigurer.defaultContentTypeStrategy()", "target": "src3387.java.ContentNegotiationConfigurer.defaultContentTypeStrategy().defaultStrategy"}, {"type": "has_parameter", "source": "src3387.java.strategies()", "target": "src3387.java.strategies().strategies"}, {"type": "has_parameter", "source": "src3387.java.favorParameter()", "target": "src3387.java.favorParameter().favorParameter"}, {"type": "has_parameter", "source": "src3387.java.parameterName()", "target": "src3387.java.parameterName().parameterName"}, {"type": "has_parameter", "source": "src3387.java.favorPathExtension()", "target": "src3387.java.favorPathExtension().favorPathExtension"}, {"type": "has_parameter", "source": "src3387.java.mediaType()", "target": "src3387.java.mediaType().extension"}, {"type": "has_parameter", "source": "src3387.java.mediaType()", "target": "src3387.java.mediaType().mediaType"}, {"type": "has_parameter", "source": "src3387.java.mediaTypes()", "target": "src3387.java.mediaTypes().mediaTypes"}, {"type": "has_parameter", "source": "src3387.java.replaceMediaTypes()", "target": "src3387.java.replaceMediaTypes().mediaTypes"}, {"type": "has_parameter", "source": "src3387.java.ignoreUnknownPathExtensions()", "target": "src3387.java.ignoreUnknownPathExtensions().ignore"}, {"type": "has_parameter", "source": "src3387.java.useJaf()", "target": "src3387.java.useJaf().useJaf"}, {"type": "has_parameter", "source": "src3387.java.useRegisteredExtensionsOnly()", "target": "src3387.java.useRegisteredExtensionsOnly().useRegisteredExtensionsOnly"}, {"type": "has_parameter", "source": "src3387.java.ignoreAcceptHeader()", "target": "src3387.java.ignoreAcceptHeader().ignoreAcceptHeader"}, {"type": "has_parameter", "source": "src3387.java.defaultContentType()", "target": "src3387.java.defaultContentType().defaultContentTypes"}, {"type": "has_parameter", "source": "src3387.java.defaultContentTypeStrategy()", "target": "src3387.java.defaultContentTypeStrategy().defaultStrategy"}]}