{"directed": true, "multigraph": false, "graph": {}, "nodes": [{"attr": {"type": "file", "name": "src8593.java", "nullable": false, "actual_type": null}, "id": "src8593.java"}, {"attr": {"type": "class", "name": "GlideRequest", "nullable": false, "actual_type": null}, "id": "src8593.java.GlideRequest"}, {"attr": {"type": "method", "name": "getDownloadOnlyRequest", "nullable": false, "actual_type": null}, "id": "src8593.java.GlideRequest.getDownloadOnlyRequest()"}, {"attr": {"type": "method", "name": "sizeMultiplier", "nullable": false, "actual_type": null}, "id": "src8593.java.GlideRequest.sizeMultiplier()"}, {"attr": {"type": "parameter", "name": "value", "nullable": false, "actual_type": "float"}, "id": "src8593.java.GlideRequest.sizeMultiplier().value"}, {"attr": {"type": "method", "name": "useUnlimitedSourceGeneratorsPool", "nullable": false, "actual_type": null}, "id": "src8593.java.GlideRequest.useUnlimitedSourceGeneratorsPool()"}, {"attr": {"type": "parameter", "name": "flag", "nullable": false, "actual_type": "boolean"}, "id": "src8593.java.GlideRequest.useUnlimitedSourceGeneratorsPool().flag"}, {"attr": {"type": "method", "name": "useAnimationPool", "nullable": false, "actual_type": null}, "id": "src8593.java.GlideRequest.useAnimationPool()"}, {"attr": {"type": "parameter", "name": "flag", "nullable": false, "actual_type": "boolean"}, "id": "src8593.java.GlideRequest.useAnimationPool().flag"}, {"attr": {"type": "method", "name": "onlyRetrieveFromCache", "nullable": false, "actual_type": null}, "id": "src8593.java.GlideRequest.onlyRetrieveFromCache()"}, {"attr": {"type": "parameter", "name": "flag", "nullable": false, "actual_type": "boolean"}, "id": "src8593.java.GlideRequest.onlyRetrieveFromCache().flag"}, {"attr": {"type": "method", "name": "diskCacheStrategy", "nullable": false, "actual_type": null}, "id": "src8593.java.GlideRequest.diskCacheStrategy()"}, {"attr": {"type": "parameter", "name": "strategy", "nullable": false, "actual_type": "DiskCacheStrategy"}, "id": "src8593.java.GlideRequest.diskCacheStrategy().strategy"}, {"attr": {"type": "method", "name": "priority", "nullable": false, "actual_type": null}, "id": "src8593.java.GlideRequest.priority()"}, {"attr": {"type": "parameter", "name": "priority", "nullable": false, "actual_type": "Priority"}, "id": "src8593.java.GlideRequest.priority().priority"}, {"attr": {"type": "method", "name": "placeholder", "nullable": false, "actual_type": null}, "id": "src8593.java.GlideRequest.placeholder()"}, {"attr": {"type": "parameter", "name": "drawable", "nullable": true, "actual_type": "Drawable"}, "id": "src8593.java.GlideRequest.placeholder().drawable"}, {"attr": {"type": "parameter", "name": "id", "nullable": false, "actual_type": "int"}, "id": "src8593.java.GlideRequest.placeholder().id"}, {"attr": {"type": "method", "name": "fallback", "nullable": false, "actual_type": null}, "id": "src8593.java.GlideRequest.fallback()"}, {"attr": {"type": "parameter", "name": "drawable", "nullable": true, "actual_type": "Drawable"}, "id": "src8593.java.GlideRequest.fallback().drawable"}, {"attr": {"type": "parameter", "name": "id", "nullable": false, "actual_type": "int"}, "id": "src8593.java.GlideRequest.fallback().id"}, {"attr": {"type": "method", "name": "error", "nullable": false, "actual_type": null}, "id": "src8593.java.GlideRequest.error()"}, {"attr": {"type": "parameter", "name": "drawable", "nullable": true, "actual_type": "Drawable"}, "id": "src8593.java.GlideRequest.error().drawable"}, {"attr": {"type": "parameter", "name": "id", "nullable": false, "actual_type": "int"}, "id": "src8593.java.GlideRequest.error().id"}, {"attr": {"type": "method", "name": "theme", "nullable": false, "actual_type": null}, "id": "src8593.java.GlideRequest.theme()"}, {"attr": {"type": "parameter", "name": "theme", "nullable": true, "actual_type": "Resources"}, "id": "src8593.java.GlideRequest.theme().theme"}, {"attr": {"type": "method", "name": "skipMemoryCache", "nullable": false, "actual_type": null}, "id": "src8593.java.GlideRequest.skipMemoryCache()"}, {"attr": {"type": "parameter", "name": "skip", "nullable": false, "actual_type": "boolean"}, "id": "src8593.java.GlideRequest.skipMemoryCache().skip"}, {"attr": {"type": "method", "name": "override", "nullable": false, "actual_type": null}, "id": "src8593.java.GlideRequest.override()"}, {"attr": {"type": "parameter", "name": "width", "nullable": false, "actual_type": "int"}, "id": "src8593.java.GlideRequest.override().width"}, {"attr": {"type": "parameter", "name": "height", "nullable": false, "actual_type": "int"}, "id": "src8593.java.GlideRequest.override().height"}, {"attr": {"type": "parameter", "name": "size", "nullable": false, "actual_type": "int"}, "id": "src8593.java.GlideRequest.override().size"}, {"attr": {"type": "method", "name": "signature", "nullable": false, "actual_type": null}, "id": "src8593.java.GlideRequest.signature()"}, {"attr": {"type": "parameter", "name": "key", "nullable": false, "actual_type": "Key"}, "id": "src8593.java.GlideRequest.signature().key"}, {"attr": {"type": "method", "name": "set", "nullable": false, "actual_type": null}, "id": "src8593.java.GlideRequest.set()"}, {"attr": {"type": "parameter", "name": "option", "nullable": false, "actual_type": "Option"}, "id": "src8593.java.GlideRequest.set().option"}, {"attr": {"type": "parameter", "name": "y", "nullable": false, "actual_type": "Y"}, "id": "src8593.java.GlideRequest.set().y"}, {"attr": {"type": "method", "name": "decode", "nullable": false, "actual_type": null}, "id": "src8593.java.GlideRequest.decode()"}, {"attr": {"type": "parameter", "name": "clazz", "nullable": false, "actual_type": "Class"}, "id": "src8593.java.GlideRequest.decode().clazz"}, {"attr": {"type": "method", "name": "encodeFormat", "nullable": false, "actual_type": null}, "id": "src8593.java.GlideRequest.encodeFormat()"}, {"attr": {"type": "parameter", "name": "format", "nullable": false, "actual_type": "Bitmap"}, "id": "src8593.java.GlideRequest.encodeFormat().format"}, {"attr": {"type": "method", "name": "encodeQuality", "nullable": false, "actual_type": null}, "id": "src8593.java.GlideRequest.encodeQuality()"}, {"attr": {"type": "parameter", "name": "value", "nullable": false, "actual_type": "int"}, "id": "src8593.java.GlideRequest.encodeQuality().value"}, {"attr": {"type": "method", "name": "frame", "nullable": false, "actual_type": null}, "id": "src8593.java.GlideRequest.frame()"}, {"attr": {"type": "parameter", "name": "value", "nullable": false, "actual_type": "long"}, "id": "src8593.java.GlideRequest.frame().value"}, {"attr": {"type": "method", "name": "format", "nullable": false, "actual_type": null}, "id": "src8593.java.GlideRequest.format()"}, {"attr": {"type": "parameter", "name": "format", "nullable": false, "actual_type": "DecodeFormat"}, "id": "src8593.java.GlideRequest.format().format"}, {"attr": {"type": "method", "name": "disallowHardwareConfig", "nullable": false, "actual_type": null}, "id": "src8593.java.GlideRequest.disallowHardwareConfig()"}, {"attr": {"type": "method", "name": "downsample", "nullable": false, "actual_type": null}, "id": "src8593.java.GlideRequest.downsample()"}, {"attr": {"type": "parameter", "name": "strategy", "nullable": false, "actual_type": "DownsampleStrategy"}, "id": "src8593.java.GlideRequest.downsample().strategy"}, {"attr": {"type": "method", "name": "timeout", "nullable": false, "actual_type": null}, "id": "src8593.java.GlideRequest.timeout()"}, {"attr": {"type": "parameter", "name": "value", "nullable": false, "actual_type": "int"}, "id": "src8593.java.GlideRequest.timeout().value"}, {"attr": {"type": "method", "name": "optionalCenterCrop", "nullable": false, "actual_type": null}, "id": "src8593.java.GlideRequest.optionalCenterCrop()"}, {"attr": {"type": "method", "name": "centerCrop", "nullable": false, "actual_type": null}, "id": "src8593.java.GlideRequest.centerCrop()"}, {"attr": {"type": "method", "name": "optionalFitCenter", "nullable": false, "actual_type": null}, "id": "src8593.java.GlideRequest.optionalFitCenter()"}, {"attr": {"type": "method", "name": "fitCenter", "nullable": false, "actual_type": null}, "id": "src8593.java.GlideRequest.fitCenter()"}, {"attr": {"type": "method", "name": "optionalCenterInside", "nullable": false, "actual_type": null}, "id": "src8593.java.GlideRequest.optionalCenterInside()"}, {"attr": {"type": "method", "name": "centerInside", "nullable": false, "actual_type": null}, "id": "src8593.java.GlideRequest.centerInside()"}, {"attr": {"type": "method", "name": "optionalCircleCrop", "nullable": false, "actual_type": null}, "id": "src8593.java.GlideRequest.optionalCircleCrop()"}, {"attr": {"type": "method", "name": "circleCrop", "nullable": false, "actual_type": null}, "id": "src8593.java.GlideRequest.circleCrop()"}, {"attr": {"type": "method", "name": "transform", "nullable": false, "actual_type": null}, "id": "src8593.java.GlideRequest.transform()"}, {"attr": {"type": "parameter", "name": "transformation", "nullable": false, "actual_type": "Transformation"}, "id": "src8593.java.GlideRequest.transform().transformation"}, {"attr": {"type": "parameter", "name": "transformations", "nullable": false, "actual_type": "Transformation"}, "id": "src8593.java.GlideRequest.transform().transformations"}, {"attr": {"type": "method", "name": "transforms", "nullable": false, "actual_type": null}, "id": "src8593.java.GlideRequest.transforms()"}, {"attr": {"type": "parameter", "name": "transformations", "nullable": false, "actual_type": "Transformation"}, "id": "src8593.java.GlideRequest.transforms().transformations"}, {"attr": {"type": "method", "name": "optionalTransform", "nullable": false, "actual_type": null}, "id": "src8593.java.GlideRequest.optionalTransform()"}, {"attr": {"type": "parameter", "name": "transformation", "nullable": false, "actual_type": "Transformation"}, "id": "src8593.java.GlideRequest.optionalTransform().transformation"}, {"attr": {"type": "parameter", "name": "clazz", "nullable": false, "actual_type": "Class"}, "id": "src8593.java.GlideRequest.optionalTransform().clazz"}, {"attr": {"type": "parameter", "name": "clazz", "nullable": false, "actual_type": "Class"}, "id": "src8593.java.GlideRequest.transform().clazz"}, {"attr": {"type": "method", "name": "dontTransform", "nullable": false, "actual_type": null}, "id": "src8593.java.GlideRequest.dontTransform()"}, {"attr": {"type": "method", "name": "dontAnimate", "nullable": false, "actual_type": null}, "id": "src8593.java.GlideRequest.dontAnimate()"}, {"attr": {"type": "method", "name": "lock", "nullable": false, "actual_type": null}, "id": "src8593.java.GlideRequest.lock()"}, {"attr": {"type": "method", "name": "autoClone", "nullable": false, "actual_type": null}, "id": "src8593.java.GlideRequest.autoClone()"}, {"attr": {"type": "method", "name": "apply", "nullable": false, "actual_type": null}, "id": "src8593.java.GlideRequest.apply()"}, {"attr": {"type": "parameter", "name": "options", "nullable": false, "actual_type": "BaseRequestOptions"}, "id": "src8593.java.GlideRequest.apply().options"}, {"attr": {"type": "method", "name": "transition", "nullable": false, "actual_type": null}, "id": "src8593.java.GlideRequest.transition()"}, {"attr": {"type": "parameter", "name": "options", "nullable": false, "actual_type": "TransitionOptions"}, "id": "src8593.java.GlideRequest.transition().options"}, {"attr": {"type": "method", "name": "listener", "nullable": false, "actual_type": null}, "id": "src8593.java.GlideRequest.listener()"}, {"attr": {"type": "parameter", "name": "listener", "nullable": true, "actual_type": "RequestListener"}, "id": "src8593.java.GlideRequest.listener().listener"}, {"attr": {"type": "method", "name": "addListener", "nullable": false, "actual_type": null}, "id": "src8593.java.GlideRequest.addListener()"}, {"attr": {"type": "parameter", "name": "listener", "nullable": true, "actual_type": "RequestListener"}, "id": "src8593.java.GlideRequest.addListener().listener"}, {"attr": {"type": "parameter", "name": "builder", "nullable": true, "actual_type": "RequestBuilder"}, "id": "src8593.java.GlideRequest.error().builder"}, {"attr": {"type": "parameter", "name": "o", "nullable": false, "actual_type": "Object"}, "id": "src8593.java.GlideRequest.error().o"}, {"attr": {"type": "method", "name": "thumbnail", "nullable": false, "actual_type": null}, "id": "src8593.java.GlideRequest.thumbnail()"}, {"attr": {"type": "parameter", "name": "builder", "nullable": true, "actual_type": "RequestBuilder"}, "id": "src8593.java.GlideRequest.thumbnail().builder"}, {"attr": {"type": "parameter", "name": "builders", "nullable": true, "actual_type": "RequestBuilder"}, "id": "src8593.java.GlideRequest.thumbnail().builders"}, {"attr": {"type": "parameter", "name": "list", "nullable": true, "actual_type": "List"}, "id": "src8593.java.GlideRequest.thumbnail().list"}, {"attr": {"type": "parameter", "name": "sizeMultiplier", "nullable": false, "actual_type": "float"}, "id": "src8593.java.GlideRequest.thumbnail().sizeMultiplier"}, {"attr": {"type": "method", "name": "load", "nullable": false, "actual_type": null}, "id": "src8593.java.GlideRequest.load()"}, {"attr": {"type": "parameter", "name": "o", "nullable": true, "actual_type": "Object"}, "id": "src8593.java.GlideRequest.load().o"}, {"attr": {"type": "parameter", "name": "bitmap", "nullable": true, "actual_type": "Bitmap"}, "id": "src8593.java.GlideRequest.load().bitmap"}, {"attr": {"type": "parameter", "name": "drawable", "nullable": true, "actual_type": "Drawable"}, "id": "src8593.java.GlideRequest.load().drawable"}, {"attr": {"type": "parameter", "name": "string", "nullable": true, "actual_type": "String"}, "id": "src8593.java.GlideRequest.load().string"}, {"attr": {"type": "parameter", "name": "uri", "nullable": true, "actual_type": "Uri"}, "id": "src8593.java.GlideRequest.load().uri"}, {"attr": {"type": "parameter", "name": "file", "nullable": true, "actual_type": "File"}, "id": "src8593.java.GlideRequest.load().file"}, {"attr": {"type": "parameter", "name": "id", "nullable": true, "actual_type": "Integer"}, "id": "src8593.java.GlideRequest.load().id"}, {"attr": {"type": "parameter", "name": "url", "nullable": true, "actual_type": "URL"}, "id": "src8593.java.GlideRequest.load().url"}, {"attr": {"type": "parameter", "name": "bytes", "nullable": true, "actual_type": "byte"}, "id": "src8593.java.GlideRequest.load().bytes"}, {"attr": {"type": "method", "name": "clone", "nullable": false, "actual_type": null}, "id": "src8593.java.GlideRequest.clone()"}, {"attr": {"type": "method", "name": "test", "nullable": false, "actual_type": null}, "id": "src8593.java.GlideRequest.test()"}], "links": [{"type": "contains", "source": "src8593.java", "target": "src8593.java.GlideRequest"}, {"type": "contains", "source": "src8593.java.GlideRequest", "target": "src8593.java.GlideRequest.getDownloadOnlyRequest()"}, {"type": "contains", "source": "src8593.java.GlideRequest", "target": "src8593.java.GlideRequest.sizeMultiplier()"}, {"type": "contains", "source": "src8593.java.GlideRequest", "target": "src8593.java.GlideRequest.useUnlimitedSourceGeneratorsPool()"}, {"type": "contains", "source": "src8593.java.GlideRequest", "target": "src8593.java.GlideRequest.useAnimationPool()"}, {"type": "contains", "source": "src8593.java.GlideRequest", "target": "src8593.java.GlideRequest.onlyRetrieveFromCache()"}, {"type": "contains", "source": "src8593.java.GlideRequest", "target": "src8593.java.GlideRequest.diskCacheStrategy()"}, {"type": "contains", "source": "src8593.java.GlideRequest", "target": "src8593.java.GlideRequest.priority()"}, {"type": "contains", "source": "src8593.java.GlideRequest", "target": "src8593.java.GlideRequest.placeholder()"}, {"type": "contains", "source": "src8593.java.GlideRequest", "target": "src8593.java.GlideRequest.fallback()"}, {"type": "contains", "source": "src8593.java.GlideRequest", "target": "src8593.java.GlideRequest.error()"}, {"type": "contains", "source": "src8593.java.GlideRequest", "target": "src8593.java.GlideRequest.theme()"}, {"type": "contains", "source": "src8593.java.GlideRequest", "target": "src8593.java.GlideRequest.skipMemoryCache()"}, {"type": "contains", "source": "src8593.java.GlideRequest", "target": "src8593.java.GlideRequest.override()"}, {"type": "contains", "source": "src8593.java.GlideRequest", "target": "src8593.java.GlideRequest.signature()"}, {"type": "contains", "source": "src8593.java.GlideRequest", "target": "src8593.java.GlideRequest.set()"}, {"type": "contains", "source": "src8593.java.GlideRequest", "target": "src8593.java.GlideRequest.decode()"}, {"type": "contains", "source": "src8593.java.GlideRequest", "target": "src8593.java.GlideRequest.encodeFormat()"}, {"type": "contains", "source": "src8593.java.GlideRequest", "target": "src8593.java.GlideRequest.encodeQuality()"}, {"type": "contains", "source": "src8593.java.GlideRequest", "target": "src8593.java.GlideRequest.frame()"}, {"type": "contains", "source": "src8593.java.GlideRequest", "target": "src8593.java.GlideRequest.format()"}, {"type": "contains", "source": "src8593.java.GlideRequest", "target": "src8593.java.GlideRequest.disallowHardwareConfig()"}, {"type": "contains", "source": "src8593.java.GlideRequest", "target": "src8593.java.GlideRequest.downsample()"}, {"type": "contains", "source": "src8593.java.GlideRequest", "target": "src8593.java.GlideRequest.timeout()"}, {"type": "contains", "source": "src8593.java.GlideRequest", "target": "src8593.java.GlideRequest.optionalCenterCrop()"}, {"type": "contains", "source": "src8593.java.GlideRequest", "target": "src8593.java.GlideRequest.centerCrop()"}, {"type": "contains", "source": "src8593.java.GlideRequest", "target": "src8593.java.GlideRequest.optionalFitCenter()"}, {"type": "contains", "source": "src8593.java.GlideRequest", "target": "src8593.java.GlideRequest.fitCenter()"}, {"type": "contains", "source": "src8593.java.GlideRequest", "target": "src8593.java.GlideRequest.optionalCenterInside()"}, {"type": "contains", "source": "src8593.java.GlideRequest", "target": "src8593.java.GlideRequest.centerInside()"}, {"type": "contains", "source": "src8593.java.GlideRequest", "target": "src8593.java.GlideRequest.optionalCircleCrop()"}, {"type": "contains", "source": "src8593.java.GlideRequest", "target": "src8593.java.GlideRequest.circleCrop()"}, {"type": "contains", "source": "src8593.java.GlideRequest", "target": "src8593.java.GlideRequest.transform()"}, {"type": "contains", "source": "src8593.java.GlideRequest", "target": "src8593.java.GlideRequest.transforms()"}, {"type": "contains", "source": "src8593.java.GlideRequest", "target": "src8593.java.GlideRequest.optionalTransform()"}, {"type": "contains", "source": "src8593.java.GlideRequest", "target": "src8593.java.GlideRequest.dontTransform()"}, {"type": "contains", "source": "src8593.java.GlideRequest", "target": "src8593.java.GlideRequest.dontAnimate()"}, {"type": "contains", "source": "src8593.java.GlideRequest", "target": "src8593.java.GlideRequest.lock()"}, {"type": "contains", "source": "src8593.java.GlideRequest", "target": "src8593.java.GlideRequest.autoClone()"}, {"type": "contains", "source": "src8593.java.GlideRequest", "target": "src8593.java.GlideRequest.apply()"}, {"type": "contains", "source": "src8593.java.GlideRequest", "target": "src8593.java.GlideRequest.transition()"}, {"type": "contains", "source": "src8593.java.GlideRequest", "target": "src8593.java.GlideRequest.listener()"}, {"type": "contains", "source": "src8593.java.GlideRequest", "target": "src8593.java.GlideRequest.addListener()"}, {"type": "contains", "source": "src8593.java.GlideRequest", "target": "src8593.java.GlideRequest.thumbnail()"}, {"type": "contains", "source": "src8593.java.GlideRequest", "target": "src8593.java.GlideRequest.load()"}, {"type": "contains", "source": "src8593.java.GlideRequest", "target": "src8593.java.GlideRequest.clone()"}, {"type": "contains", "source": "src8593.java.GlideRequest", "target": "src8593.java.GlideRequest.test()"}, {"type": "has_parameter", "source": "src8593.java.GlideRequest.sizeMultiplier()", "target": "src8593.java.GlideRequest.sizeMultiplier().value"}, {"type": "has_parameter", "source": "src8593.java.GlideRequest.useUnlimitedSourceGeneratorsPool()", "target": "src8593.java.GlideRequest.useUnlimitedSourceGeneratorsPool().flag"}, {"type": "has_parameter", "source": "src8593.java.GlideRequest.useAnimationPool()", "target": "src8593.java.GlideRequest.useAnimationPool().flag"}, {"type": "has_parameter", "source": "src8593.java.GlideRequest.onlyRetrieveFromCache()", "target": "src8593.java.GlideRequest.onlyRetrieveFromCache().flag"}, {"type": "has_parameter", "source": "src8593.java.GlideRequest.diskCacheStrategy()", "target": "src8593.java.GlideRequest.diskCacheStrategy().strategy"}, {"type": "has_parameter", "source": "src8593.java.GlideRequest.priority()", "target": "src8593.java.GlideRequest.priority().priority"}, {"type": "has_parameter", "source": "src8593.java.GlideRequest.placeholder()", "target": "src8593.java.GlideRequest.placeholder().drawable"}, {"type": "has_parameter", "source": "src8593.java.GlideRequest.placeholder()", "target": "src8593.java.GlideRequest.placeholder().id"}, {"type": "has_parameter", "source": "src8593.java.GlideRequest.fallback()", "target": "src8593.java.GlideRequest.fallback().drawable"}, {"type": "has_parameter", "source": "src8593.java.GlideRequest.fallback()", "target": "src8593.java.GlideRequest.fallback().id"}, {"type": "has_parameter", "source": "src8593.java.GlideRequest.error()", "target": "src8593.java.GlideRequest.error().drawable"}, {"type": "has_parameter", "source": "src8593.java.GlideRequest.error()", "target": "src8593.java.GlideRequest.error().id"}, {"type": "has_parameter", "source": "src8593.java.GlideRequest.error()", "target": "src8593.java.GlideRequest.error().builder"}, {"type": "has_parameter", "source": "src8593.java.GlideRequest.error()", "target": "src8593.java.GlideRequest.error().o"}, {"type": "has_parameter", "source": "src8593.java.GlideRequest.theme()", "target": "src8593.java.GlideRequest.theme().theme"}, {"type": "has_parameter", "source": "src8593.java.GlideRequest.skipMemoryCache()", "target": "src8593.java.GlideRequest.skipMemoryCache().skip"}, {"type": "has_parameter", "source": "src8593.java.GlideRequest.override()", "target": "src8593.java.GlideRequest.override().width"}, {"type": "has_parameter", "source": "src8593.java.GlideRequest.override()", "target": "src8593.java.GlideRequest.override().height"}, {"type": "has_parameter", "source": "src8593.java.GlideRequest.override()", "target": "src8593.java.GlideRequest.override().size"}, {"type": "has_parameter", "source": "src8593.java.GlideRequest.signature()", "target": "src8593.java.GlideRequest.signature().key"}, {"type": "has_parameter", "source": "src8593.java.GlideRequest.set()", "target": "src8593.java.GlideRequest.set().option"}, {"type": "has_parameter", "source": "src8593.java.GlideRequest.set()", "target": "src8593.java.GlideRequest.set().y"}, {"type": "has_parameter", "source": "src8593.java.GlideRequest.decode()", "target": "src8593.java.GlideRequest.decode().clazz"}, {"type": "has_parameter", "source": "src8593.java.GlideRequest.encodeFormat()", "target": "src8593.java.GlideRequest.encodeFormat().format"}, {"type": "has_parameter", "source": "src8593.java.GlideRequest.encodeQuality()", "target": "src8593.java.GlideRequest.encodeQuality().value"}, {"type": "has_parameter", "source": "src8593.java.GlideRequest.frame()", "target": "src8593.java.GlideRequest.frame().value"}, {"type": "has_parameter", "source": "src8593.java.GlideRequest.format()", "target": "src8593.java.GlideRequest.format().format"}, {"type": "has_parameter", "source": "src8593.java.GlideRequest.downsample()", "target": "src8593.java.GlideRequest.downsample().strategy"}, {"type": "has_parameter", "source": "src8593.java.GlideRequest.timeout()", "target": "src8593.java.GlideRequest.timeout().value"}, {"type": "has_parameter", "source": "src8593.java.GlideRequest.transform()", "target": "src8593.java.GlideRequest.transform().transformation"}, {"type": "has_parameter", "source": "src8593.java.GlideRequest.transform()", "target": "src8593.java.GlideRequest.transform().transformations"}, {"type": "has_parameter", "source": "src8593.java.GlideRequest.transform()", "target": "src8593.java.GlideRequest.transform().clazz"}, {"type": "has_parameter", "source": "src8593.java.GlideRequest.transforms()", "target": "src8593.java.GlideRequest.transforms().transformations"}, {"type": "has_parameter", "source": "src8593.java.GlideRequest.optionalTransform()", "target": "src8593.java.GlideRequest.optionalTransform().transformation"}, {"type": "has_parameter", "source": "src8593.java.GlideRequest.optionalTransform()", "target": "src8593.java.GlideRequest.optionalTransform().clazz"}, {"type": "has_parameter", "source": "src8593.java.GlideRequest.apply()", "target": "src8593.java.GlideRequest.apply().options"}, {"type": "has_parameter", "source": "src8593.java.GlideRequest.transition()", "target": "src8593.java.GlideRequest.transition().options"}, {"type": "has_parameter", "source": "src8593.java.GlideRequest.listener()", "target": "src8593.java.GlideRequest.listener().listener"}, {"type": "has_parameter", "source": "src8593.java.GlideRequest.addListener()", "target": "src8593.java.GlideRequest.addListener().listener"}, {"type": "has_parameter", "source": "src8593.java.GlideRequest.thumbnail()", "target": "src8593.java.GlideRequest.thumbnail().builder"}, {"type": "has_parameter", "source": "src8593.java.GlideRequest.thumbnail()", "target": "src8593.java.GlideRequest.thumbnail().builders"}, {"type": "has_parameter", "source": "src8593.java.GlideRequest.thumbnail()", "target": "src8593.java.GlideRequest.thumbnail().list"}, {"type": "has_parameter", "source": "src8593.java.GlideRequest.thumbnail()", "target": "src8593.java.GlideRequest.thumbnail().sizeMultiplier"}, {"type": "has_parameter", "source": "src8593.java.GlideRequest.load()", "target": "src8593.java.GlideRequest.load().o"}, {"type": "has_parameter", "source": "src8593.java.GlideRequest.load()", "target": "src8593.java.GlideRequest.load().bitmap"}, {"type": "has_parameter", "source": "src8593.java.GlideRequest.load()", "target": "src8593.java.GlideRequest.load().drawable"}, {"type": "has_parameter", "source": "src8593.java.GlideRequest.load()", "target": "src8593.java.GlideRequest.load().string"}, {"type": "has_parameter", "source": "src8593.java.GlideRequest.load()", "target": "src8593.java.GlideRequest.load().uri"}, {"type": "has_parameter", "source": "src8593.java.GlideRequest.load()", "target": "src8593.java.GlideRequest.load().file"}, {"type": "has_parameter", "source": "src8593.java.GlideRequest.load()", "target": "src8593.java.GlideRequest.load().id"}, {"type": "has_parameter", "source": "src8593.java.GlideRequest.load()", "target": "src8593.java.GlideRequest.load().url"}, {"type": "has_parameter", "source": "src8593.java.GlideRequest.load()", "target": "src8593.java.GlideRequest.load().bytes"}]}