{"directed": true, "multigraph": false, "graph": {}, "nodes": [{"attr": {"type": "file", "name": "src9209.java", "line_number": null, "nullable": false, "actual_type": null}, "id": "src9209.java"}, {"attr": {"type": "class", "name": "UserRepresentationModelAssembler", "line_number": 22, "nullable": false, "actual_type": null}, "id": "src9209.java.UserRepresentationModelAssembler"}, {"attr": {"type": "method", "name": "getServerUri", "line_number": 27, "nullable": false, "actual_type": null}, "id": "src9209.java.UserRepresentationModelAssembler.getServerUri()"}, {"attr": {"type": "parameter", "name": "exchange", "line_number": 27, "nullable": true, "actual_type": "ServerWebExchange"}, "id": "src9209.java.UserRepresentationModelAssembler.getServerUri().exchange"}, {"attr": {"type": "method", "name": "toModel", "line_number": 40, "nullable": false, "actual_type": null}, "id": "src9209.java.UserRepresentationModelAssembler.toModel()"}, {"attr": {"type": "parameter", "name": "entity", "line_number": 40, "nullable": false, "actual_type": "UserEntity"}, "id": "src9209.java.UserRepresentationModelAssembler.toModel().entity"}, {"attr": {"type": "parameter", "name": "exchange", "line_number": 40, "nullable": false, "actual_type": "ServerWebExchange"}, "id": "src9209.java.UserRepresentationModelAssembler.toModel().exchange"}, {"attr": {"type": "method", "name": "entityToModel", "line_number": 44, "nullable": false, "actual_type": null}, "id": "src9209.java.UserRepresentationModelAssembler.entityToModel()"}, {"attr": {"type": "parameter", "name": "entity", "line_number": 44, "nullable": false, "actual_type": "UserEntity"}, "id": "src9209.java.UserRepresentationModelAssembler.entityToModel().entity"}, {"attr": {"type": "parameter", "name": "exchange", "line_number": 44, "nullable": false, "actual_type": "ServerWebExchange"}, "id": "src9209.java.UserRepresentationModelAssembler.entityToModel().exchange"}, {"attr": {"type": "method", "name": "getModel", "line_number": 60, "nullable": false, "actual_type": null}, "id": "src9209.java.UserRepresentationModelAssembler.getModel()"}, {"attr": {"type": "parameter", "name": "m", "line_number": 60, "nullable": false, "actual_type": "Mono"}, "id": "src9209.java.UserRepresentationModelAssembler.getModel().m"}, {"attr": {"type": "parameter", "name": "exchange", "line_number": 60, "nullable": false, "actual_type": "ServerWebExchange"}, "id": "src9209.java.UserRepresentationModelAssembler.getModel().exchange"}, {"attr": {"type": "method", "name": "toListModel", "line_number": 71, "nullable": false, "actual_type": null}, "id": "src9209.java.UserRepresentationModelAssembler.toListModel()"}, {"attr": {"type": "parameter", "name": "entities", "line_number": 71, "nullable": false, "actual_type": "Flux"}, "id": "src9209.java.UserRepresentationModelAssembler.toListModel().entities"}, {"attr": {"type": "parameter", "name": "exchange", "line_number": 71, "nullable": false, "actual_type": "ServerWebExchange"}, "id": "src9209.java.UserRepresentationModelAssembler.toListModel().exchange"}, {"attr": {"type": "field", "name": "serverUri", "line_number": null, "nullable": false, "actual_type": null}, "id": "src9209.java.UserRepresentationModelAssembler.serverUri"}, {"attr": {"type": "variable", "name": "serverUri", "line_number": null, "nullable": false, "actual_type": null}, "id": "src9209.java.serverUri"}, {"attr": {"type": "literal", "name": "null", "line_number": 25, "nullable": false, "actual_type": null}, "id": "src9209.java.null_25_37"}, {"attr": {"type": "method", "name": "getServerUri", "line_number": 27, "nullable": false, "actual_type": null}, "id": "src9209.java.getServerUri()"}, {"attr": {"type": "parameter", "name": "exchange", "line_number": 27, "nullable": true, "actual_type": "ServerWebExchange"}, "id": "src9209.java.getServerUri().exchange"}, {"attr": {"type": "method", "name": "toModel", "line_number": 40, "nullable": false, "actual_type": null}, "id": "src9209.java.toModel()"}, {"attr": {"type": "parameter", "name": "entity", "line_number": 40, "nullable": false, "actual_type": "UserEntity"}, "id": "src9209.java.toModel().entity"}, {"attr": {"type": "parameter", "name": "exchange", "line_number": 40, "nullable": false, "actual_type": "ServerWebExchange"}, "id": "src9209.java.toModel().exchange"}, {"attr": {"type": "method", "name": "entityToModel", "line_number": 44, "nullable": false, "actual_type": null}, "id": "src9209.java.entityToModel()"}, {"attr": {"type": "parameter", "name": "entity", "line_number": 44, "nullable": false, "actual_type": "UserEntity"}, "id": "src9209.java.entityToModel().entity"}, {"attr": {"type": "parameter", "name": "exchange", "line_number": 44, "nullable": false, "actual_type": "ServerWebExchange"}, "id": "src9209.java.entityToModel().exchange"}, {"attr": {"type": "variable", "name": "resource", "line_number": null, "nullable": false, "actual_type": null}, "id": "src9209.java.resource"}, {"attr": {"type": "method", "name": "getModel", "line_number": 60, "nullable": false, "actual_type": null}, "id": "src9209.java.getModel()"}, {"attr": {"type": "parameter", "name": "m", "line_number": 60, "nullable": false, "actual_type": "Mono"}, "id": "src9209.java.getModel().m"}, {"attr": {"type": "parameter", "name": "exchange", "line_number": 60, "nullable": false, "actual_type": "ServerWebExchange"}, "id": "src9209.java.getModel().exchange"}, {"attr": {"type": "variable", "name": "model", "line_number": null, "nullable": false, "actual_type": null}, "id": "src9209.java.model"}, {"attr": {"type": "method", "name": "toListModel", "line_number": 71, "nullable": false, "actual_type": null}, "id": "src9209.java.toListModel()"}, {"attr": {"type": "parameter", "name": "entities", "line_number": 71, "nullable": false, "actual_type": "Flux"}, "id": "src9209.java.toListModel().entities"}, {"attr": {"type": "parameter", "name": "exchange", "line_number": 71, "nullable": false, "actual_type": "ServerWebExchange"}, "id": "src9209.java.toListModel().exchange"}], "links": [{"type": "contains", "source": "src9209.java", "target": "src9209.java.UserRepresentationModelAssembler"}, {"type": "has_field", "source": "src9209.java", "target": "src9209.java.serverUri"}, {"type": "contains", "source": "src9209.java.UserRepresentationModelAssembler", "target": "src9209.java.UserRepresentationModelAssembler.getServerUri()"}, {"type": "contains", "source": "src9209.java.UserRepresentationModelAssembler", "target": "src9209.java.UserRepresentationModelAssembler.toModel()"}, {"type": "contains", "source": "src9209.java.UserRepresentationModelAssembler", "target": "src9209.java.UserRepresentationModelAssembler.entityToModel()"}, {"type": "contains", "source": "src9209.java.UserRepresentationModelAssembler", "target": "src9209.java.UserRepresentationModelAssembler.getModel()"}, {"type": "contains", "source": "src9209.java.UserRepresentationModelAssembler", "target": "src9209.java.UserRepresentationModelAssembler.toListModel()"}, {"type": "has_field", "source": "src9209.java.UserRepresentationModelAssembler", "target": "src9209.java.UserRepresentationModelAssembler.serverUri"}, {"type": "has_parameter", "source": "src9209.java.UserRepresentationModelAssembler.getServerUri()", "target": "src9209.java.UserRepresentationModelAssembler.getServerUri().exchange"}, {"type": "has_parameter", "source": "src9209.java.UserRepresentationModelAssembler.toModel()", "target": "src9209.java.UserRepresentationModelAssembler.toModel().entity"}, {"type": "has_parameter", "source": "src9209.java.UserRepresentationModelAssembler.toModel()", "target": "src9209.java.UserRepresentationModelAssembler.toModel().exchange"}, {"type": "has_parameter", "source": "src9209.java.UserRepresentationModelAssembler.entityToModel()", "target": "src9209.java.UserRepresentationModelAssembler.entityToModel().entity"}, {"type": "has_parameter", "source": "src9209.java.UserRepresentationModelAssembler.entityToModel()", "target": "src9209.java.UserRepresentationModelAssembler.entityToModel().exchange"}, {"type": "has_parameter", "source": "src9209.java.UserRepresentationModelAssembler.getModel()", "target": "src9209.java.UserRepresentationModelAssembler.getModel().m"}, {"type": "has_parameter", "source": "src9209.java.UserRepresentationModelAssembler.getModel()", "target": "src9209.java.UserRepresentationModelAssembler.getModel().exchange"}, {"type": "has_parameter", "source": "src9209.java.UserRepresentationModelAssembler.toListModel()", "target": "src9209.java.UserRepresentationModelAssembler.toListModel().entities"}, {"type": "has_parameter", "source": "src9209.java.UserRepresentationModelAssembler.toListModel()", "target": "src9209.java.UserRepresentationModelAssembler.toListModel().exchange"}, {"type": "has_parameter", "source": "src9209.java.getServerUri()", "target": "src9209.java.getServerUri().exchange"}, {"type": "has_parameter", "source": "src9209.java.toModel()", "target": "src9209.java.toModel().entity"}, {"type": "has_parameter", "source": "src9209.java.toModel()", "target": "src9209.java.toModel().exchange"}, {"type": "has_parameter", "source": "src9209.java.entityToModel()", "target": "src9209.java.entityToModel().entity"}, {"type": "has_parameter", "source": "src9209.java.entityToModel()", "target": "src9209.java.entityToModel().exchange"}, {"type": "has_parameter", "source": "src9209.java.getModel()", "target": "src9209.java.getModel().m"}, {"type": "has_parameter", "source": "src9209.java.getModel()", "target": "src9209.java.getModel().exchange"}, {"type": "has_parameter", "source": "src9209.java.toListModel()", "target": "src9209.java.toListModel().entities"}, {"type": "has_parameter", "source": "src9209.java.toListModel()", "target": "src9209.java.toListModel().exchange"}]}